[{"heart_rate":85.0,"heart_rate_max":89.0,"heart_rate_min":83.0,"start_time":1727344740000,"end_time":1727344799000},{"heart_rate":85.0,"heart_rate_max":88.0,"heart_rate_min":84.0,"start_time":1727344680000,"end_time":1727344739000},{"heart_rate":83.0,"heart_rate_max":86.0,"heart_rate_min":79.0,"start_time":1727344620000,"end_time":1727344679000},{"heart_rate":88.0,"heart_rate_max":96.0,"heart_rate_min":86.0,"start_time":1727344560000,"end_time":1727344619000},{"heart_rate":85.0,"heart_rate_max":88.0,"heart_rate_min":84.0,"start_time":1727344500000,"end_time":1727344559000},{"heart_rate":84.0,"heart_rate_max":87.0,"heart_rate_min":83.0,"start_time":1727344440000,"end_time":1727344499000},{"heart_rate":86.0,"heart_rate_max":91.0,"heart_rate_min":82.0,"start_time":1727344380000,"end_time":1727344439000},{"heart_rate":89.0,"heart_rate_max":98.0,"heart_rate_min":86.0,"start_time":1727344320000,"end_time":1727344379000},{"heart_rate":88.0,"heart_rate_max":91.0,"heart_rate_min":86.0,"start_time":1727344260000,"end_time":1727344319000},{"heart_rate":86.0,"heart_rate_max":89.0,"heart_rate_min":83.0,"start_time":1727344200000,"end_time":1727344259000},{"heart_rate":88.0,"heart_rate_max":91.0,"heart_rate_min":87.0,"start_time":1727344140000,"end_time":1727344199000},{"heart_rate":86.0,"heart_rate_max":90.0,"heart_rate_min":84.0,"start_time":1727344080000,"end_time":1727344139000},{"heart_rate":87.0,"heart_rate_max":89.0,"heart_rate_min":85.0,"start_time":1727344020000,"end_time":1727344079000},{"heart_rate":87.0,"heart_rate_max":91.0,"heart_rate_min":85.0,"start_time":1727343960000,"end_time":1727344019000},{"heart_rate":88.0,"heart_rate_max":92.0,"heart_rate_min":85.0,"start_time":1727343900000,"end_time":1727343959000},{"heart_rate":90.0,"heart_rate_max":93.0,"heart_rate_min":86.0,"start_time":1727343840000,"end_time":1727343899000},{"heart_rate":85.0,"heart_rate_max":87.0,"heart_rate_min":83.0,"start_time":1727343780000,"end_time":1727343839000},{"heart_rate":87.0,"heart_rate_max":92.0,"heart_rate_min":83.0,"start_time":1727343720000,"end_time":1727343779000},{"heart_rate":87.0,"heart_rate_max":95.0,"heart_rate_min":83.0,"start_time":1727343660000,"end_time":1727343719000},{"heart_rate":89.0,"heart_rate_max":92.0,"heart_rate_min":87.0,"start_time":1727343600000,"end_time":1727343659000},{"heart_rate":86.0,"heart_rate_max":89.0,"heart_rate_min":83.0,"start_time":1727343540000,"end_time":1727343599000},{"heart_rate":91.0,"heart_rate_max":105.0,"heart_rate_min":89.0,"start_time":1727343480000,"end_time":1727343539000},{"heart_rate":90.0,"heart_rate_max":97.0,"heart_rate_min":88.0,"start_time":1727343420000,"end_time":1727343479000},{"heart_rate":90.0,"heart_rate_max":95.0,"heart_rate_min":88.0,"start_time":1727343360000,"end_time":1727343419000},{"heart_rate":87.0,"heart_rate_max":92.0,"heart_rate_min":85.0,"start_time":1727343300000,"end_time":1727343359000},{"heart_rate":91.0,"heart_rate_max":97.0,"heart_rate_min":87.0,"start_time":1727343240000,"end_time":1727343299000},{"heart_rate":86.0,"heart_rate_max":88.0,"heart_rate_min":84.0,"start_time":1727343180000,"end_time":1727343239000},{"heart_rate":87.0,"heart_rate_max":90.0,"heart_rate_min":85.0,"start_time":1727343120000,"end_time":1727343179000},{"heart_rate":88.0,"heart_rate_max":90.0,"heart_rate_min":86.0,"start_time":1727343060000,"end_time":1727343119000},{"heart_rate":87.0,"heart_rate_max":89.0,"heart_rate_min":87.0,"start_time":1727343000000,"end_time":1727343059000},{"heart_rate":87.0,"heart_rate_max":90.0,"heart_rate_min":86.0,"start_time":1727342940000,"end_time":1727342999000},{"heart_rate":87.0,"heart_rate_max":88.0,"heart_rate_min":86.0,"start_time":1727342880000,"end_time":1727342939000},{"heart_rate":87.0,"heart_rate_max":92.0,"heart_rate_min":85.0,"start_time":1727342820000,"end_time":1727342879000},{"heart_rate":88.0,"heart_rate_max":94.0,"heart_rate_min":86.0,"start_time":1727342760000,"end_time":1727342819000},{"heart_rate":91.0,"heart_rate_max":97.0,"heart_rate_min":88.0,"start_time":1727342700000,"end_time":1727342759000},{"heart_rate":87.0,"heart_rate_max":92.0,"heart_rate_min":84.0,"start_time":1727342640000,"end_time":1727342699000},{"heart_rate":90.0,"heart_rate_max":99.0,"heart_rate_min":85.0,"start_time":1727342580000,"end_time":1727342639000},{"heart_rate":88.0,"heart_rate_max":92.0,"heart_rate_min":85.0,"start_time":1727342520000,"end_time":1727342579000},{"heart_rate":88.0,"heart_rate_max":91.0,"heart_rate_min":87.0,"start_time":1727342460000,"end_time":1727342519000},{"heart_rate":90.0,"heart_rate_max":91.0,"heart_rate_min":89.0,"start_time":1727342400000,"end_time":1727342459000},{"heart_rate":89.0,"heart_rate_max":90.0,"heart_rate_min":88.0,"start_time":1727342340000,"end_time":1727342399000},{"heart_rate":89.0,"heart_rate_max":90.0,"heart_rate_min":88.0,"start_time":1727342280000,"end_time":1727342339000},{"heart_rate":89.0,"heart_rate_max":90.0,"heart_rate_min":89.0,"start_time":1727342220000,"end_time":1727342279000},{"heart_rate":89.0,"heart_rate_max":90.0,"heart_rate_min":88.0,"start_time":1727342160000,"end_time":1727342219000},{"heart_rate":89.0,"heart_rate_max":90.0,"heart_rate_min":88.0,"start_time":1727342100000,"end_time":1727342159000},{"heart_rate":88.0,"heart_rate_max":90.0,"heart_rate_min":87.0,"start_time":1727342040000,"end_time":1727342099000},{"heart_rate":88.0,"heart_rate_max":91.0,"heart_rate_min":87.0,"start_time":1727341980000,"end_time":1727342039000},{"heart_rate":89.0,"heart_rate_max":90.0,"heart_rate_min":88.0,"start_time":1727341920000,"end_time":1727341979000},{"heart_rate":88.0,"heart_rate_max":89.0,"heart_rate_min":88.0,"start_time":1727341860000,"end_time":1727341919000},{"heart_rate":88.0,"heart_rate_max":90.0,"heart_rate_min":88.0,"start_time":1727341800000,"end_time":1727341859000},{"heart_rate":87.0,"heart_rate_max":89.0,"heart_rate_min":87.0,"start_time":1727341740000,"end_time":1727341799000},{"heart_rate":87.0,"heart_rate_max":89.0,"heart_rate_min":86.0,"start_time":1727341680000,"end_time":1727341739000},{"heart_rate":87.0,"heart_rate_max":89.0,"heart_rate_min":87.0,"start_time":1727341620000,"end_time":1727341679000},{"heart_rate":88.0,"heart_rate_max":89.0,"heart_rate_min":88.0,"start_time":1727341560000,"end_time":1727341619000},{"heart_rate":87.0,"heart_rate_max":90.0,"heart_rate_min":86.0,"start_time":1727341500000,"end_time":1727341559000},{"heart_rate":89.0,"heart_rate_max":90.0,"heart_rate_min":88.0,"start_time":1727341440000,"end_time":1727341499000},{"heart_rate":89.0,"heart_rate_max":90.0,"heart_rate_min":88.0,"start_time":1727341380000,"end_time":1727341439000},{"heart_rate":89.0,"heart_rate_max":90.0,"heart_rate_min":89.0,"start_time":1727341320000,"end_time":1727341379000},{"heart_rate":88.0,"heart_rate_max":91.0,"heart_rate_min":87.0,"start_time":1727341260000,"end_time":1727341319000},{"heart_rate":87.0,"heart_rate_max":90.0,"heart_rate_min":86.0,"start_time":1727341200000,"end_time":1727341259000}]