[{"score":49,"score_max":52,"score_min":44,"flag":1,"level":1,"start_time":1756066440000,"end_time":1756066499000},{"score":46,"score_max":53,"score_min":43,"flag":1,"level":1,"start_time":1756066380000,"end_time":1756066439000},{"score":53,"score_max":55,"score_min":53,"flag":1,"level":1,"start_time":1756066320000,"end_time":1756066379000},{"score":43,"score_max":53,"score_min":34,"flag":1,"level":1,"start_time":1756066260000,"end_time":1756066319000},{"score":48,"score_max":65,"score_min":34,"flag":1,"level":1,"start_time":1756066200000,"end_time":1756066259000},{"score":51,"score_max":65,"score_min":40,"flag":1,"level":1,"start_time":1756066140000,"end_time":1756066199000},{"score":48,"score_max":54,"score_min":42,"flag":1,"level":1,"start_time":1756066080000,"end_time":1756066139000},{"score":50,"score_max":53,"score_min":48,"flag":1,"level":1,"start_time":1756066020000,"end_time":1756066079000},{"score":50,"score_max":53,"score_min":48,"flag":1,"level":1,"start_time":1756065960000,"end_time":1756066019000},{"score":44,"score_max":48,"score_min":44,"flag":1,"level":1,"start_time":1756065900000,"end_time":1756065959000},{"score":50,"score_max":52,"score_min":45,"flag":1,"level":1,"start_time":1756065840000,"end_time":1756065899000},{"score":48,"score_max":51,"score_min":46,"flag":1,"level":1,"start_time":1756065780000,"end_time":1756065839000},{"score":49,"score_max":51,"score_min":46,"flag":1,"level":1,"start_time":1756065720000,"end_time":1756065779000},{"score":53,"score_max":59,"score_min":41,"flag":1,"level":1,"start_time":1756065660000,"end_time":1756065719000},{"score":49,"score_max":55,"score_min":45,"flag":1,"level":1,"start_time":1756065600000,"end_time":1756065659000}]