{"hourlyDataList":[{"moveHourly":true,"startTime":1762070400000},{"moveHourly":true,"startTime":1762081200000},{"moveHourly":true,"startTime":1762084800000},{"moveHourly":true,"startTime":1762092000000},{"moveHourly":true,"startTime":1762099200000},{"moveHourly":true,"startTime":1762102800000},{"moveHourly":true,"startTime":1762106400000},{"moveHourly":true,"startTime":1762110000000}],"mAdaptiveGoal":0,"mIsGoalAchieved":false,"mIsMostActiveAchieved":false,"mMostActiveMinutes":0,"mStreakDayCount":0,"mUnitDataList":[{"distance":4.250414,"dynamicActiveTime":0,"exerciseCalorie":0.0,"exerciseTime":0,"floorCount":0,"mCalorie":0.18024576,"mOthersTime":0,"mRunTime":0,"mStartTime":30000000,"mTimeUnit":600000,"mWalkTime":4002,"runStep":0,"walkStep":6},{"distance":256.15204,"dynamicActiveTime":0,"exerciseCalorie":0.0,"exerciseTime":0,"floorCount":0,"mCalorie":11.126516,"mOthersTime":0,"mRunTime":0,"mStartTime":30600000,"mTimeUnit":600000,"mWalkTime":226053,"runStep":0,"walkStep":368},{"distance":136.99481,"dynamicActiveTime":0,"exerciseCalorie":0.0,"exerciseTime":0,"floorCount":0,"mCalorie":6.529689,"mOthersTime":0,"mRunTime":2400,"mStartTime":31200000,"mTimeUnit":600000,"mWalkTime":111389,"runStep":6,"walkStep":167},{"distance":192.97067,"dynamicActiveTime":0,"exerciseCalorie":0.0,"exerciseTime":0,"floorCount":0,"mCalorie":8.24601,"mOthersTime":0,"mRunTime":0,"mStartTime":31800000,"mTimeUnit":600000,"mWalkTime":154017,"runStep":0,"walkStep":274},{"distance":6.0906982,"dynamicActiveTime":0,"exerciseCalorie":0.0,"exerciseTime":0,"floorCount":0,"mCalorie":0.27644348,"mOthersTime":0,"mRunTime":0,"mStartTime":38400000,"mTimeUnit":600000,"mWalkTime":6003,"runStep":0,"walkStep":9},{"distance":19.279724,"dynamicActiveTime":0,"exerciseCalorie":0.0,"exerciseTime":0,"floorCount":0,"mCalorie":1.0206642,"mOthersTime":0,"mRunTime":800,"mStartTime":40200000,"mTimeUnit":600000,"mWalkTime":12006,"runStep":2,"walkStep":18},{"distance":306.69916,"dynamicActiveTime":0,"exerciseCalorie":0.0,"exerciseTime":0,"floorCount":0,"mCalorie":13.28834,"mOthersTime":0,"mRunTime":0,"mStartTime":45600000,"mTimeUnit":600000,"mWalkTime":249368,"runStep":0,"walkStep":440},{"distance":388.0498,"dynamicActiveTime":0,"exerciseCalorie":0.0,"exerciseTime":0,"floorCount":0,"mCalorie":16.968918,"mOthersTime":0,"mRunTime":0,"mStartTime":46200000,"mTimeUnit":600000,"mWalkTime":320040,"runStep":0,"walkStep":560},{"distance":4.0235596,"dynamicActiveTime":0,"exerciseCalorie":0.0,"exerciseTime":0,"floorCount":0,"mCalorie":0.18706512,"mOthersTime":0,"mRunTime":0,"mStartTime":49200000,"mTimeUnit":600000,"mWalkTime":4002,"runStep":0,"walkStep":6},{"distance":176.86462,"dynamicActiveTime":0,"exerciseCalorie":0.0,"exerciseTime":0,"floorCount":0,"mCalorie":7.6350555,"mOthersTime":0,"mRunTime":0,"mStartTime":50400000,"mTimeUnit":600000,"mWalkTime":152713,"runStep":0,"walkStep":253},{"distance":29.555664,"dynamicActiveTime":0,"exerciseCalorie":0.0,"exerciseTime":0,"floorCount":0,"mCalorie":1.6452866,"mOthersTime":0,"mRunTime":2000,"mStartTime":59400000,"mTimeUnit":600000,"mWalkTime":16008,"runStep":5,"walkStep":24},{"distance":139.5166,"dynamicActiveTime":0,"exerciseCalorie":0.0,"exerciseTime":0,"floorCount":0,"mCalorie":6.090523,"mOthersTime":0,"mRunTime":0,"mStartTime":63600000,"mTimeUnit":600000,"mWalkTime":117362,"runStep":0,"walkStep":201},{"distance":26.193237,"dynamicActiveTime":0,"exerciseCalorie":0.0,"exerciseTime":0,"floorCount":0,"mCalorie":1.1567535,"mOthersTime":0,"mRunTime":0,"mStartTime":64200000,"mTimeUnit":600000,"mWalkTime":25346,"runStep":0,"walkStep":38},{"distance":45.916016,"dynamicActiveTime":0,"exerciseCalorie":0.0,"exerciseTime":0,"floorCount":0,"mCalorie":2.4081116,"mOthersTime":0,"mRunTime":400,"mStartTime":64800000,"mTimeUnit":600000,"mWalkTime":32683,"runStep":1,"walkStep":49},{"distance":64.56897,"dynamicActiveTime":0,"exerciseCalorie":0.0,"exerciseTime":0,"floorCount":0,"mCalorie":2.767784,"mOthersTime":0,"mRunTime":0,"mStartTime":65400000,"mTimeUnit":600000,"mWalkTime":61364,"runStep":0,"walkStep":92},{"distance":39.028076,"dynamicActiveTime":0,"exerciseCalorie":0.0,"exerciseTime":0,"floorCount":0,"mCalorie":1.6914978,"mOthersTime":0,"mRunTime":0,"mStartTime":66000000,"mTimeUnit":600000,"mWalkTime":37352,"runStep":0,"walkStep":56},{"distance":34.334595,"dynamicActiveTime":0,"exerciseCalorie":0.0,"exerciseTime":0,"floorCount":0,"mCalorie":1.482666,"mOthersTime":0,"mRunTime":0,"mStartTime":66600000,"mTimeUnit":600000,"mWalkTime":32683,"runStep":0,"walkStep":49},{"distance":185.77722,"dynamicActiveTime":0,"exerciseCalorie":0.0,"exerciseTime":0,"floorCount":0,"mCalorie":7.92408,"mOthersTime":0,"mRunTime":0,"mStartTime":69600000,"mTimeUnit":600000,"mWalkTime":158019,"runStep":0,"walkStep":264},{"distance":8.411133,"dynamicActiveTime":0,"exerciseCalorie":0.0,"exerciseTime":0,"floorCount":0,"mCalorie":0.3603897,"mOthersTime":0,"mRunTime":0,"mStartTime":70800000,"mTimeUnit":600000,"mWalkTime":8004,"runStep":0,"walkStep":12},{"distance":4.0844727,"dynamicActiveTime":0,"exerciseCalorie":0.0,"exerciseTime":0,"floorCount":0,"mCalorie":0.18360901,"mOthersTime":0,"mRunTime":0,"mStartTime":81000000,"mTimeUnit":600000,"mWalkTime":4002,"runStep":0,"walkStep":6}],"version":1}