[{"heart_rate":80.0,"heart_rate_max":81.0,"heart_rate_min":79.0,"start_time":1732193940000,"end_time":1732193999000},{"heart_rate":80.0,"heart_rate_max":82.0,"heart_rate_min":78.0,"start_time":1732193880000,"end_time":1732193939000},{"heart_rate":79.0,"heart_rate_max":82.0,"heart_rate_min":78.0,"start_time":1732193820000,"end_time":1732193879000},{"heart_rate":79.0,"heart_rate_max":82.0,"heart_rate_min":78.0,"start_time":1732193760000,"end_time":1732193819000},{"heart_rate":79.0,"heart_rate_max":82.0,"heart_rate_min":79.0,"start_time":1732193700000,"end_time":1732193759000},{"heart_rate":80.0,"heart_rate_max":83.0,"heart_rate_min":79.0,"start_time":1732193640000,"end_time":1732193699000},{"heart_rate":79.0,"heart_rate_max":81.0,"heart_rate_min":78.0,"start_time":1732193580000,"end_time":1732193639000},{"heart_rate":79.0,"heart_rate_max":83.0,"heart_rate_min":77.0,"start_time":1732193520000,"end_time":1732193579000},{"heart_rate":80.0,"heart_rate_max":82.0,"heart_rate_min":78.0,"start_time":1732193460000,"end_time":1732193519000},{"heart_rate":80.0,"heart_rate_max":82.0,"heart_rate_min":78.0,"start_time":1732193400000,"end_time":1732193459000},{"heart_rate":79.0,"heart_rate_max":82.0,"heart_rate_min":77.0,"start_time":1732193340000,"end_time":1732193399000},{"heart_rate":79.0,"heart_rate_max":84.0,"heart_rate_min":77.0,"start_time":1732193280000,"end_time":1732193339000},{"heart_rate":81.0,"heart_rate_max":83.0,"heart_rate_min":79.0,"start_time":1732193220000,"end_time":1732193279000},{"heart_rate":80.0,"heart_rate_max":82.0,"heart_rate_min":78.0,"start_time":1732193160000,"end_time":1732193219000},{"heart_rate":81.0,"heart_rate_max":83.0,"heart_rate_min":80.0,"start_time":1732193100000,"end_time":1732193159000},{"heart_rate":82.0,"heart_rate_max":84.0,"heart_rate_min":81.0,"start_time":1732193040000,"end_time":1732193099000},{"heart_rate":81.0,"heart_rate_max":84.0,"heart_rate_min":79.0,"start_time":1732192980000,"end_time":1732193039000},{"heart_rate":80.0,"heart_rate_max":81.0,"heart_rate_min":77.0,"start_time":1732192920000,"end_time":1732192979000},{"heart_rate":77.0,"heart_rate_max":80.0,"heart_rate_min":76.0,"start_time":1732192860000,"end_time":1732192919000},{"heart_rate":78.0,"heart_rate_max":81.0,"heart_rate_min":77.0,"start_time":1732192800000,"end_time":1732192859000},{"heart_rate":78.0,"heart_rate_max":81.0,"heart_rate_min":77.0,"start_time":1732192740000,"end_time":1732192799000},{"heart_rate":78.0,"heart_rate_max":81.0,"heart_rate_min":76.0,"start_time":1732192680000,"end_time":1732192739000},{"heart_rate":79.0,"heart_rate_max":81.0,"heart_rate_min":78.0,"start_time":1732192620000,"end_time":1732192679000},{"heart_rate":78.0,"heart_rate_max":81.0,"heart_rate_min":75.0,"start_time":1732192560000,"end_time":1732192619000},{"heart_rate":78.0,"heart_rate_max":80.0,"heart_rate_min":76.0,"start_time":1732192500000,"end_time":1732192559000},{"heart_rate":78.0,"heart_rate_max":81.0,"heart_rate_min":76.0,"start_time":1732192440000,"end_time":1732192499000},{"heart_rate":76.0,"heart_rate_max":78.0,"heart_rate_min":74.0,"start_time":1732192380000,"end_time":1732192439000},{"heart_rate":78.0,"heart_rate_max":80.0,"heart_rate_min":76.0,"start_time":1732192320000,"end_time":1732192379000},{"heart_rate":77.0,"heart_rate_max":81.0,"heart_rate_min":75.0,"start_time":1732192260000,"end_time":1732192319000},{"heart_rate":78.0,"heart_rate_max":86.0,"heart_rate_min":72.0,"start_time":1732192200000,"end_time":1732192259000},{"heart_rate":82.0,"heart_rate_max":85.0,"heart_rate_min":79.0,"start_time":1732192140000,"end_time":1732192199000},{"heart_rate":81.0,"heart_rate_max":83.0,"heart_rate_min":78.0,"start_time":1732192080000,"end_time":1732192139000},{"heart_rate":84.0,"heart_rate_max":87.0,"heart_rate_min":79.0,"start_time":1732192020000,"end_time":1732192079000},{"heart_rate":76.0,"heart_rate_max":79.0,"heart_rate_min":76.0,"start_time":1732191960000,"end_time":1732192019000},{"heart_rate":77.0,"heart_rate_max":84.0,"heart_rate_min":73.0,"start_time":1732191900000,"end_time":1732191959000},{"heart_rate":79.0,"heart_rate_max":83.0,"heart_rate_min":74.0,"start_time":1732191840000,"end_time":1732191899000},{"heart_rate":79.0,"heart_rate_max":83.0,"heart_rate_min":73.0,"start_time":1732191780000,"end_time":1732191839000},{"heart_rate":78.0,"heart_rate_max":91.0,"heart_rate_min":68.0,"start_time":1732191720000,"end_time":1732191779000},{"heart_rate":80.0,"heart_rate_max":83.0,"heart_rate_min":78.0,"start_time":1732191660000,"end_time":1732191719000},{"heart_rate":83.0,"heart_rate_max":86.0,"heart_rate_min":81.0,"start_time":1732191600000,"end_time":1732191659000},{"heart_rate":79.0,"heart_rate_max":83.0,"heart_rate_min":76.0,"start_time":1732191540000,"end_time":1732191599000},{"heart_rate":80.0,"heart_rate_max":84.0,"heart_rate_min":77.0,"start_time":1732191480000,"end_time":1732191539000},{"heart_rate":78.0,"heart_rate_max":81.0,"heart_rate_min":77.0,"start_time":1732191420000,"end_time":1732191479000},{"heart_rate":79.0,"heart_rate_max":82.0,"heart_rate_min":77.0,"start_time":1732191360000,"end_time":1732191419000},{"heart_rate":79.0,"heart_rate_max":81.0,"heart_rate_min":78.0,"start_time":1732191300000,"end_time":1732191359000},{"heart_rate":80.0,"heart_rate_max":84.0,"heart_rate_min":77.0,"start_time":1732191240000,"end_time":1732191299000},{"heart_rate":80.0,"heart_rate_max":87.0,"heart_rate_min":76.0,"start_time":1732191180000,"end_time":1732191239000},{"heart_rate":84.0,"heart_rate_max":86.0,"heart_rate_min":83.0,"start_time":1732191120000,"end_time":1732191179000},{"heart_rate":80.0,"heart_rate_max":84.0,"heart_rate_min":78.0,"start_time":1732191060000,"end_time":1732191119000},{"heart_rate":77.0,"heart_rate_max":80.0,"heart_rate_min":76.0,"start_time":1732191000000,"end_time":1732191059000},{"heart_rate":80.0,"heart_rate_max":83.0,"heart_rate_min":77.0,"start_time":1732190940000,"end_time":1732190999000},{"heart_rate":78.0,"heart_rate_max":82.0,"heart_rate_min":74.0,"start_time":1732190880000,"end_time":1732190939000},{"heart_rate":82.0,"heart_rate_max":88.0,"heart_rate_min":76.0,"start_time":1732190820000,"end_time":1732190879000},{"heart_rate":80.0,"heart_rate_max":84.0,"heart_rate_min":75.0,"start_time":1732190760000,"end_time":1732190819000},{"heart_rate":78.0,"heart_rate_max":82.0,"heart_rate_min":76.0,"start_time":1732190700000,"end_time":1732190759000},{"heart_rate":83.0,"heart_rate_max":89.0,"heart_rate_min":76.0,"start_time":1732190640000,"end_time":1732190699000},{"heart_rate":83.0,"heart_rate_max":87.0,"heart_rate_min":81.0,"start_time":1732190580000,"end_time":1732190639000},{"heart_rate":83.0,"heart_rate_max":86.0,"heart_rate_min":82.0,"start_time":1732190520000,"end_time":1732190579000},{"heart_rate":82.0,"heart_rate_max":84.0,"heart_rate_min":80.0,"start_time":1732190460000,"end_time":1732190519000},{"heart_rate":79.0,"heart_rate_max":82.0,"heart_rate_min":77.0,"start_time":1732190400000,"end_time":1732190459000}]